fds/__init__.py
fds/sdk/__init__.py
fds/sdk/DocumentsDistributorDocuments/__init__.py
fds/sdk/DocumentsDistributorDocuments/api_client.py
fds/sdk/DocumentsDistributorDocuments/configuration.py
fds/sdk/DocumentsDistributorDocuments/exceptions.py
fds/sdk/DocumentsDistributorDocuments/model_utils.py
fds/sdk/DocumentsDistributorDocuments/rest.py
fds/sdk/DocumentsDistributorDocuments/api/__init__.py
fds/sdk/DocumentsDistributorDocuments/api/global_filings_api_api.py
fds/sdk/DocumentsDistributorDocuments/api/news_api_api.py
fds/sdk/DocumentsDistributorDocuments/api/street_account_xml_api_api.py
fds/sdk/DocumentsDistributorDocuments/apis/__init__.py
fds/sdk/DocumentsDistributorDocuments/model/__init__.py
fds/sdk/DocumentsDistributorDocuments/model/checkstatus.py
fds/sdk/DocumentsDistributorDocuments/model/checkstatus_response.py
fds/sdk/DocumentsDistributorDocuments/model/checkstatusone.py
fds/sdk/DocumentsDistributorDocuments/model/filings_files.py
fds/sdk/DocumentsDistributorDocuments/model/filings_response.py
fds/sdk/DocumentsDistributorDocuments/model/getfiles.py
fds/sdk/DocumentsDistributorDocuments/model/getfiles_response.py
fds/sdk/DocumentsDistributorDocuments/model/getfilesone.py
fds/sdk/DocumentsDistributorDocuments/model/is_partial_one.py
fds/sdk/DocumentsDistributorDocuments/model/meta_one.py
fds/sdk/DocumentsDistributorDocuments/model/news_status.py
fds/sdk/DocumentsDistributorDocuments/model/newscheckstatus_response.py
fds/sdk/DocumentsDistributorDocuments/model/newsgetfiles_response.py
fds/sdk/DocumentsDistributorDocuments/model/newsrequestfiles_response.py
fds/sdk/DocumentsDistributorDocuments/model/pagination_one.py
fds/sdk/DocumentsDistributorDocuments/model/requestfiles_response.py
fds/sdk/DocumentsDistributorDocuments/model/status.py
fds/sdk/DocumentsDistributorDocuments/model/street_account_status.py
fds/sdk/DocumentsDistributorDocuments/models/__init__.py
fds.sdk.DocumentsDistributorDocuments-0.22.1.dist-info/LICENSE
fds.sdk.DocumentsDistributorDocuments-0.22.1.dist-info/METADATA
fds.sdk.DocumentsDistributorDocuments-0.22.1.dist-info/WHEEL
fds.sdk.DocumentsDistributorDocuments-0.22.1.dist-info/top_level.txt
fds.sdk.DocumentsDistributorDocuments-0.22.1.dist-info/RECORD
